Workbook

Sheet Instrucciones
A1: KineFit — Plan de pruebas del entorno de pruebas
A3: Este plan es el criterio de salida a producción. Si se completa según lo definido aquí, el sistema está listo para producción; si no se completa, no sale.
A5: Cómo se usa
A6: 1. Sembrar la base del entorno de pruebas con seed_pruebas.sql antes de cada ronda.
A7: 2. Ejecutar los casos en el orden de las hojas. Cada ejecutor completa sólo las filas donde figura como responsable.
A8: 3. Registrar el resultado en la columna Resultado y adjuntar evidencia: captura, registro o enlace.
A9: 4. Todo caso Fallido genera una fila en la hoja Hallazgos con su severidad.
A10: 5. Corregido el hallazgo, el caso se vuelve a ejecutar. No se marca Aprobado sin repetir la prueba.
A12: Responsables
A13: Maxi — pruebas funcionales del panel, ventas, fichas y documentos.
A14: Jhoan — pruebas funcionales del sitio público y de la configuración de contenido.
A15: Claude — pruebas técnicas: concurrencia, carga, autorización, seguridad y auditoría del sitio.
... A28: Las reservas del sitio permanecen desactivadas en producción durante la marcha blanca, pero el flujo de reserva se prueba completo en el entorno de pruebas.

Sheet Resumen
A1: Resumen de ejecución
A3: Indicador | B3: Funcionales | C3: No funcionales | D3: Total
A4: Casos totales | B4: =COUNTA('Pruebas funcionales'!$K$2:$K$223) -> 222 | C4: =COUNTA('Pruebas no funcionales'!$K$2:$K$64) -> 63 | D4: =B4+C4 -> 285
A5: Pendientes | B5: =COUNTIF('Pruebas funcionales'!$K$2:$K$223,"Pendiente") -> 222 | C5: =COUNTIF('Pruebas no funcionales'!$K$2:$K$64,"Pendiente") -> 63 | D5: =B5+C5 -> 285
A6: Aprobados | B6: =COUNTIF('Pruebas funcionales'!$K$2:$K$223,"Aprobado") -> 0 | C6: =COUNTIF('Pruebas no funcionales'!$K$2:$K$64,"Aprobado") -> 0 | D6: =B6+C6 -> 0
A7: Fallidos | B7: =COUNTIF('Pruebas funcionales'!$K$2:$K$223,"Fallido") -> 0 | C7: =COUNTIF('Pruebas no funcionales'!$K$2:$K$64,"Fallido") -> 0 | D7: =B7+C7 -> 0
A8: Bloqueados | B8: =COUNTIF('Pruebas funcionales'!$K$2:$K$223,"Bloqueado") -> 0 | C8: =COUNTIF('Pruebas no funcionales'!$K$2:$K$64,"Bloqueado") -> 0 | D8: =B8+C8 -> 0
A9: No aplica | B9: =COUNTIF('Pruebas funcionales'!$K$2:$K$223,"No aplica") -> 0 | C9: =COUNTIF('Pruebas no funcionales'!$K$2:$K$64,"No aplica") -> 0 | D9: =B9+C9 -> 0
A10: Fallidos bloqueantes | B10: =COUNTIFS('Pruebas funcionales'!$I$2:$I$223,"Bloqueante",'Pruebas funcionales'!$K$2:$K$223,"Fallido") -> 0 | C10: =COUNTIFS('Pruebas no funcionales'!$I$2:$I$64,"Bloqueante",'Pruebas no funcionales'!$K$2:$K$64,"Fallido") -> 0 | D10: =B10+C10 -> 0
A11: Fallidos críticos | B11: =COUNTIFS('Pruebas funcionales'!$I$2:$I$223,"Crítico",'Pruebas funcionales'!$K$2:$K$223,"Fallido") -> 0 | C11: =COUNTIFS('Pruebas no funcionales'!$I$2:$I$64,"Crítico",'Pruebas no funcionales'!$K$2:$K$64,"Fallido") -> 0 | D11: =B11+C11 -> 0
A12: Fallidos mayores | B12: =COUNTIFS('Pruebas funcionales'!$I$2:$I$223,"Mayor",'Pruebas funcionales'!$K$2:$K$223,"Fallido") -> 0 | C12: =COUNTIFS('Pruebas no funcionales'!$I$2:$I$64,"Mayor",'Pruebas no funcionales'!$K$2:$K$64,"Fallido") -> 0 | D12: =B12+C12 -> 0
A14: Avance de ejecución | B14: =IF($D$4=0,0,($D$4-$D$5)/$D$4) -> 0
A16: Estado del plan | B16: =IF(AND($D$5=0,$D$10=0,$D$11=0),"APROBADO — listo para producción","NO APROBADO") -> NO APROBADO
A17: Regla de cierre: cero pendientes, cero fallidos bloqueantes y cero fallidos críticos.

Sheet Datos de prueba
A1: Set de datos determinista del entorno de pruebas
A3: Entidad | B3: Registro | C3: Detalle
A4: Servicios | B4: Masajes | C4: Activo. Duración 60 minutos.
A5: Servicios | B5: Masajes Premium | C5: Activo. Duración 90 minutos.
A6: Servicios | B6: Masajes en pareja | C6: Activo. Duración 60 minutos.
A7: Servicios | B7: Masajes Reductivos | C7: Activo. Duración 30 minutos.
A8: Servicios | B8: Embarazadas | C8: Activo. Duración 60 minutos.
A9: Servicios | B9: Kinesiología | C9: Inactivo al sembrar, para probar su activación.
A10: Servicios | B10: Voucher para Regalo | C10: Activo, sin duración.
A11: Especialistas | B11: Especialista A | C11: Jornada completa. Habilitada en todos los servicios.
A12: Especialistas | B12: Especialista B | C12: 09:00 a 17:00. Habilitada sólo en masoterapia.
A13: Especialistas | B13: Especialista C | C13: 18:00 a 21:00. Habilitada en masoterapia y kinesiología.
A14: Cuentas | B14: Administrador | C14: Cuenta de administrador del entorno de pruebas.
... A34: Bloqueos | B34: Bloqueo sin motivo público | C34: Para verificar que el motivo interno no se expone.

Sheet Pruebas funcionales
A1: ID | B1: Historia | C1: Módulo | D1: Caso de prueba | E1: Precondición | F1: Pasos | G1: Datos de entrada | H1: Resultado esperado | I1: Severidad si falla | J1: Responsable | K1: Resultado | L1: Evidencia | M1: Observaciones
A2: PF-001 | B2: AUT-001 | C2: Autenticación paciente | D2: Navegar el flujo completo sin sesión iniciada | E2: Formulario de reserva habilitado | F2: Abrir el sitio sin sesión. Seleccionar servicio, fecha, hora y especialista. | G2: Servicio: Masajes | H2: El flujo avanza hasta el último paso sin pedir sesión en ningún momento | I2: Mayor | J2: Maxi | K2: Pendiente
A3: PF-002 | B3: AUT-001 | C3: Autenticación paciente | D3: Solicitud de sesión al confirmar la reserva | E3: Flujo completado hasta selección de especialista | F3: Presionar confirmar reserva | G3: - | H3: El sistema muestra el aviso de inicio de sesión con Google antes de pasar al pago | I3: Crítico | J3: Maxi | K3: Pendiente
A4: PF-003 | B4: AUT-001 | C4: Autenticación paciente | D4: Alta de paciente nuevo desde Google | E4: Cuenta de Google sin paciente asociado | F4: Iniciar sesión con una cuenta de Google no registrada | G4: Correo de prueba nuevo | H4: Se crea el registro de paciente vinculado a la identidad de Google | I4: Crítico | J4: Maxi | K4: Pendiente
A5: PF-004 | B5: AUT-001 | C5: Autenticación paciente | D5: Solicitud de RUT y teléfono en el primer ingreso | E5: Paciente nuevo autenticado | F5: Observar el formulario posterior al inicio de sesión | G5: - | H5: El sistema solicita RUT y teléfono antes de continuar al pago | I5: Crítico | J5: Maxi | K5: Pendiente
A6: PF-005 | B6: AUT-001 | C6: Autenticación paciente | D6: Precarga de datos en reserva posterior | E6: Paciente ya registrado con RUT y teléfono | F6: Iniciar una segunda reserva con la misma cuenta | G6: - | H6: RUT y teléfono aparecen precargados y no se vuelven a solicitar | I6: Mayor | J6: Maxi | K6: Pendiente
A7: PF-006 | B7: AUT-001 | C7: Autenticación paciente | D7: Rechazo de RUT inválido | E7: En el paso de datos personales | F7: Ingresar un RUT con dígito verificador incorrecto | G7: 12.345.678-9 | H7: El sistema rechaza el RUT y no permite continuar | I7: Mayor | J7: Maxi | K7: Pendiente
A8: PF-007 | B8: AUT-001 | C8: Autenticación paciente | D8: Token de Google inválido | E8: - | F8: Enviar al backend un ID token manipulado | G8: Token alterado | H8: El backend rechaza la operación, no crea paciente y no ocupa bloques | I8: Bloqueante | J8: Claude | K8: Pendiente
A9: PF-008 | B9: AUT-001 | C9: Autenticación paciente | D9: Sesión expirada al reservar | E9: Sesión de paciente vencida | F9: Intentar confirmar una reserva con la sesión vencida | G9: - | H9: La operación se rechaza con mensaje claro y los bloques quedan disponibles | I9: Crítico | J9: Claude | K9: Pendiente
A10: PF-009 | B10: AUT-001 | C10: Autenticación paciente | D10: Aviso de tratamiento de datos | E10: Paciente nuevo | F10: Completar el alta de cuenta | G10: - | H10: Se muestra el aviso de tratamiento de datos y se registra el consentimiento | I10: Crítico | J10: Maxi | K10: Pendiente
A11: PF-010 | B11: AGE-001 | C11: Reserva web | D11: Orden del flujo | E11: Formulario habilitado | F11: Recorrer el flujo de reserva | G11: - | H11: El orden es servicio, fecha, hora y finalmente especialista | I11: Mayor | J11: Maxi | K11: Pendiente
A12: PF-011 | B12: AGE-001 | C12: Reserva web | D12: Catálogo publicado | E12: Servicios activos en el panel | F12: Abrir el selector de servicios | G12: - | H12: Se listan todas las categorías al mismo nivel, sin subcategorías | I12: Mayor | J12: Maxi | K12: Pendiente
A13: PF-012 | B13: AGE-001 | C13: Reserva web | D13: Servicio inactivo no se ofrece | E13: Un servicio desactivado en el panel | F13: Abrir el selector de servicios | G13: Kinesiología inactiva | H13: El servicio inactivo no aparece en el selector | I13: Crítico | J13: Maxi | K13: Pendiente
... A223: PF-222 | B223: NOT-001 | C223: Notificaciones | D223: Reintento ante fallo | E223: Servicio de correo caído | F223: Provocar un fallo de envío | G223: - | H223: El envío queda como fallido y se reintenta sin interrumpir la operación | I223: Crítico | J223: Claude | K223: Pendiente

Sheet Pruebas no funcionales
A1: ID | B1: Historia | C1: Módulo | D1: Caso de prueba | E1: Precondición | F1: Pasos | G1: Datos de entrada | H1: Resultado esperado | I1: Severidad si falla | J1: Responsable | K1: Resultado | L1: Evidencia | M1: Observaciones
A2: PNF-001 | B2: NFR-001 | C2: Rendimiento | D2: Tiempo de respuesta del sitio público | E2: Entorno de pruebas desplegado | F2: Medir la carga de la portada y del selector de disponibilidad | G2: - | H2: La página responde dentro del umbral acordado en carga normal | I2: Mayor | J2: Claude | K2: Pendiente
A3: PNF-002 | B3: NFR-001 | C3: Rendimiento | D3: Tiempo de respuesta del panel | E3: Sesión de administrador | F3: Medir la carga de agenda, ventas y pacientes | G3: - | H3: Las vistas responden sin degradar la operación diaria | I3: Mayor | J3: Claude | K3: Pendiente
A4: PNF-003 | B4: NFR-001 | C4: Rendimiento | D4: Consulta de disponibilidad concurrente | E4: Agenda con datos | F4: Lanzar peticiones concurrentes sostenidas al endpoint de disponibilidad | G4: 50 usuarios simultáneos | H4: No hay errores ni degradación perceptible | I4: Crítico | J4: Claude | K4: Pendiente
A5: PNF-004 | B5: NFR-001 | C5: Fiabilidad | D5: Doble reserva simultánea | E5: Un bloque disponible | F5: Enviar dos confirmaciones simultáneas sobre el mismo bloque | G5: 2 peticiones en paralelo | H5: Sólo una prospera; la otra recibe rechazo claro y no hay doble ocupación | I5: Bloqueante | J5: Claude | K5: Pendiente
A6: PNF-005 | B6: NFR-001 | C6: Fiabilidad | D6: Doble reserva en ráfaga | E6: Un bloque disponible | F6: Enviar veinte confirmaciones simultáneas sobre el mismo bloque | G6: 20 peticiones | H6: Exactamente una cita queda registrada | I6: Bloqueante | J6: Claude | K6: Pendiente
A7: PNF-006 | B7: NFR-001 | C7: Fiabilidad | D7: Concurrencia sobre la misma cita | E7: Cita confirmada | F7: Dos usuarios del panel cambian su estado a la vez | G7: - | H7: El resultado es consistente y queda una sola traza coherente | I7: Crítico | J7: Claude | K7: Pendiente
A8: PNF-007 | B8: NFR-001 | C8: Fiabilidad | D8: Caída de la pasarela | E8: Pasarela inaccesible | F8: Intentar pagar | G8: - | H8: Se informa el problema, no quedan citas inconsistentes y los bloques se liberan | I8: Crítico | J8: Claude | K8: Pendiente
A9: PNF-008 | B9: NFR-001 | C9: Fiabilidad | D9: Caída del almacenamiento de imágenes | E9: Servicio inaccesible | F9: Abrir el sitio | G9: - | H9: El sitio sigue operativo y no muestra errores visibles | I9: Mayor | J9: Claude | K9: Pendiente
A10: PNF-009 | B10: NFR-001 | C10: Fiabilidad | D10: Fallo del servicio de correo | E10: Servicio inaccesible | F10: Confirmar una cita | G10: - | H10: La cita se confirma y el envío queda registrado como fallido para reintento | I10: Crítico | J10: Claude | K10: Pendiente
A11: PNF-010 | B11: NFR-001 | C11: Fiabilidad | D11: Errores sin fuga de información | E11: - | F11: Provocar un error del servidor | G11: - | H11: El mensaje al usuario no expone trazas internas ni datos sensibles | I11: Crítico | J11: Claude | K11: Pendiente
A12: PNF-011 | B12: NFR-001 | C12: Fiabilidad | D12: Consola limpia | E12: Sitio y panel desplegados | F12: Recorrer las vistas principales revisando la consola | G12: - | H12: No hay errores en la consola del navegador | I12: Mayor | J12: Claude | K12: Pendiente
A13: PNF-012 | B13: NFR-001 | C13: Usabilidad | D13: Sitio en móvil | E13: Sitio desplegado | F13: Recorrer el sitio en resolución móvil | G13: - | H13: Todo el contenido es legible y operable | I13: Mayor | J13: Claude | K13: Pendiente
... A64: PNF-063 | B64: WEB-001 | C64: Calidad del sitio | D64: Ninguna URL de entorno expuesta | E64: Sitio desplegado | F64: Revisar enlaces y peticiones | G64: - | H64: No aparecen URL de entornos de despliegue intermedios | I64: Mayor | J64: Claude | K64: Pendiente

Sheet Hallazgos
A1: ID | B1: Caso de origen | C1: Descripción del hallazgo | D1: Severidad | E1: Detectado por | F1: Fecha detección | G1: Responsable de corrección | H1: Estado | I1: Fecha cierre | J1: Notas
A2: H-001 | B2: PF-000 | C2: Ejemplo: reemplazar esta fila al registrar el primer hallazgo | D2: Mayor | E2: Maxi | G2: Maxi | H2: Abierto
